aspars/__init__.py
aspars/__main__.py
aspars/aspars.py
aspars-0.1.0.dist-info/LICENSE
aspars-0.1.0.dist-info/METADATA
aspars-0.1.0.dist-info/WHEEL
aspars-0.1.0.dist-info/top_level.txt
aspars-0.1.0.dist-info/RECORD
