Metadata-Version: 2.1
Name: aspars
Version: 0.1.0
Summary: ASPars allows to parse Answer Sets into python structures
Home-page: https://github.com/finalfire/aspars
Author: Francesco Cauteruccio
Author-email: f.cauteruccio@gmail.com
License: MIT
Platform: UNKNOWN
Classifier: License :: OSI Approved :: MIT License
Classifier: Programming Language :: Python :: 3
Classifier: Programming Language :: Python :: 3.7
Requires-Dist: lark
